{".class":"MypyFile","_fullname":"pydantic._internal._fields","future_import_flags":["annotations"],"is_partial_stub_package":false,"is_stub":false,"names":{".class":"SymbolTable","Any":{".class":"SymbolTableNode","cross_ref":"typing.Any","kind":"Gdef","module_hidden":true,"module_public":false},"BaseModel":{".class":"SymbolTableNode","cross_ref":"pydantic.main.BaseModel","kind":"Gdef","module_hidden":true,"module_public":false},"ConfigWrapper":{".class":"SymbolTableNode","cross_ref":"pydantic._internal._config.ConfigWrapper","kind":"Gdef","module_hidden":true,"module_public":false},"FieldInfo":{".class":"SymbolTableNode","cross_ref":"pydantic.fields.FieldInfo","kind":"Gdef","module_hidden":true,"module_public":false},"PydanticGeneralMetadata":{".class":"SymbolTableNode","kind":"Gdef","node":{".class":"TypeInfo","_promote":[],"abstract_attributes":[],"alt_promote":null,"bases":["pydantic._internal._fields.PydanticMetadata"],"dataclass_transform_spec":null,"declared_metaclass":null,"defn":{".class":"ClassDef","fullname":"pydantic._internal._fields.PydanticGeneralMetadata","name":"PydanticGeneralMetadata","type_vars":[]},"deletable_attributes":[],"flags":[],"fullname":"pydantic._internal._fields.PydanticGeneralMetadata","has_param_spec_type":false,"metaclass_type":null,"metadata":{},"module_name":"pydantic._internal._fields","mro":["pydantic._internal._fields.PydanticGeneralMetadata","pydantic._internal._fields.PydanticMetadata","pydantic._internal._repr.Representation","builtins.object"],"names":{".class":"SymbolTable","__init__":{".class":"SymbolTableNode","kind":"Mdef","node":{".class":"FuncDef","abstract_status":0,"arg_kinds":[0,4],"arg_names":["self","metadata"],"dataclass_transform_spec":null,"flags":[],"fullname":"pydantic._internal._fields.PydanticGeneralMetadata.__init__","name":"__init__","type":{".class":"CallableType","arg_kinds":[0,4],"arg_names":["self","metadata"],"arg_types":["pydantic._internal._fields.PydanticGeneralMetadata",{".class":"AnyType","missing_import_name":null,"source_any":null,"type_of_any":2}],"bound_args":[],"def_extras":{"first_arg":"self"},"fallback":"builtins.function","from_concatenate":false,"implicit":false,"is_ellipsis_args":false,"name":"__init__ of PydanticGeneralMetadata","ret_type":{".class":"NoneType"},"type_guard":null,"unpack_kwargs":false,"variables":[]}}}},"self_type":null,"slots":null,"tuple_type":null,"type_vars":[],"typeddict_type":null}},"PydanticMetadata":{".class":"SymbolTableNode","kind":"Gdef","node":{".class":"TypeInfo","_promote":[],"abstract_attributes":[],"alt_promote":null,"bases":["pydantic._internal._repr.Representation"],"dataclass_transform_spec":null,"declared_metaclass":null,"defn":{".class":"ClassDef","fullname":"pydantic._internal._fields.PydanticMetadata","name":"PydanticMetadata","type_vars":[]},"deletable_attributes":[],"flags":[],"fullname":"pydantic._internal._fields.PydanticMetadata","has_param_spec_type":false,"metaclass_type":null,"metadata":{},"module_name":"pydantic._internal._fields","mro":["pydantic._internal._fields.PydanticMetadata","pydantic._internal._repr.Representation","builtins.object"],"names":{".class":"SymbolTable","__slots__":{".class":"SymbolTableNode","kind":"Mdef","node":{".class":"Var","flags":["is_initialized_in_class","is_inferred","has_explicit_value","allow_incompatible_override"],"fullname":"pydantic._internal._fields.PydanticMetadata.__slots__","name":"__slots__","type":{".class":"TupleType","implicit":false,"items":[],"partial_fallback":{".class":"Instance","args":[{".class":"AnyType","missing_import_name":null,"source_any":null,"type_of_any":6}],"type_ref":"builtins.tuple"}}}}},"self_type":null,"slots":null,"tuple_type":null,"type_vars":[],"typeddict_type":null}},"PydanticUndefined":{".class":"SymbolTableNode","cross_ref":"pydantic_core._pydantic_core.PydanticUndefined","kind":"Gdef","module_hidden":true,"module_public":false},"Representation":{".class":"SymbolTableNode","cross_ref":"pydantic._internal._repr.Representation","kind":"Gdef","module_hidden":true,"module_public":false},"StandardDataclass":{".class":"SymbolTableNode","cross_ref":"pydantic._internal._dataclasses.StandardDataclass","kind":"Gdef","module_hidden":true,"module_public":false},"TYPE_CHECKING":{".class":"SymbolTableNode","cross_ref":"typing.TYPE_CHECKING","kind":"Gdef","module_hidden":true,"module_public":false},"__annotations__":{".class":"SymbolTableNode","kind":"Gdef","node":{".class":"Var","flags":["is_ready"],"fullname":"pydantic._internal._fields.__annotations__","name":"__annotations__","type":{".class":"Instance","args":["builtins.str",{".class":"AnyType","missing_import_name":null,"source_any":null,"type_of_any":6}],"type_ref":"builtins.dict"}}},"__doc__":{".class":"SymbolTableNode","kind":"Gdef","node":{".class":"Var","flags":["is_ready"],"fullname":"pydantic._internal._fields.__doc__","name":"__doc__","type":"builtins.str"}},"__file__":{".class":"SymbolTableNode","kind":"Gdef","node":{".class":"Var","flags":["is_ready"],"fullname":"pydantic._internal._fields.__file__","name":"__file__","type":"builtins.str"}},"__name__":{".class":"SymbolTableNode","kind":"Gdef","node":{".class":"Var","flags":["is_ready"],"fullname":"pydantic._internal._fields.__name__","name":"__name__","type":"builtins.str"}},"__package__":{".class":"SymbolTableNode","kind":"Gdef","node":{".class":"Var","flags":["is_ready"],"fullname":"pydantic._internal._fields.__package__","name":"__package__","type":"builtins.str"}},"_annotations":{".class":"SymbolTableNode","cross_ref":"__future__.annotations","kind":"Gdef","module_hidden":true,"module_public":false},"_is_finalvar_with_default_val":{".class":"SymbolTableNode","kind":"Gdef","node":{".class":"FuncDef","abstract_status":0,"arg_kinds":[0,0],"arg_names":["type_","val"],"dataclass_transform_spec":null,"flags":[],"fullname":"pydantic._internal._fields._is_finalvar_with_default_val","name":"_is_finalvar_with_default_val","type":{".class":"CallableType","arg_kinds":[0,0],"arg_names":["type_","val"],"arg_types":[{".class":"TypeType","item":{".class":"AnyType","missing_import_name":null,"source_any":null,"type_of_any":2}},{".class":"AnyType","missing_import_name":null,"source_any":null,"type_of_any":2}],"bound_args":[],"def_extras":{"first_arg":null},"fallback":"builtins.function","from_concatenate":false,"implicit":false,"is_ellipsis_args":false,"name":"_is_finalvar_with_default_val","ret_type":"builtins.bool","type_guard":null,"unpack_kwargs":false,"variables":[]}}},"_typing_extra":{".class":"SymbolTableNode","cross_ref":"pydantic._internal._typing_extra","kind":"Gdef","module_hidden":true,"module_public":false},"collect_dataclass_fields":{".class":"SymbolTableNode","kind":"Gdef","node":{".class":"FuncDef","abstract_status":0,"arg_kinds":[0,0,5],"arg_names":["cls","types_namespace","typevars_map"],"dataclass_transform_spec":null,"flags":[],"fullname":"pydantic._internal._fields.collect_dataclass_fields","name":"collect_dataclass_fields","type":{".class":"CallableType","arg_kinds":[0,0,5],"arg_names":["cls","types_namespace","typevars_map"],"arg_types":[{".class":"TypeType","item":"pydantic._internal._dataclasses.StandardDataclass"},{".class":"UnionType","items":[{".class":"Instance","args":["builtins.str",{".class":"AnyType","missing_import_name":null,"source_any":null,"type_of_any":2}],"type_ref":"builtins.dict"},{".class":"NoneType"}]},{".class":"UnionType","items":[{".class":"Instance","args":[{".class":"AnyType","missing_import_name":null,"source_any":null,"type_of_any":2},{".class":"AnyType","missing_import_name":null,"source_any":null,"type_of_any":2}],"type_ref":"builtins.dict"},{".class":"NoneType"}]}],"bound_args":[],"def_extras":{"first_arg":null},"fallback":"builtins.function","from_concatenate":false,"implicit":false,"is_ellipsis_args":false,"name":"collect_dataclass_fields","ret_type":{".class":"Instance","args":["builtins.str","pydantic.fields.FieldInfo"],"type_ref":"builtins.dict"},"type_guard":null,"unpack_kwargs":false,"variables":[]}}},"collect_model_fields":{".class":"SymbolTableNode","kind":"Gdef","node":{".class":"FuncDef","abstract_status":0,"arg_kinds":[0,0,0,0,5],"arg_names":["cls","bases","config_wrapper","types_namespace","typevars_map"],"dataclass_transform_spec":null,"flags":[],"fullname":"pydantic._internal._fields.collect_model_fields","name":"collect_model_fields","type":{".class":"CallableType","arg_kinds":[0,0,0,0,5],"arg_names":["cls","bases","config_wrapper","types_namespace","typevars_map"],"arg_types":[{".class":"TypeType","item":"pydantic.main.BaseModel"},{".class":"Instance","args":[{".class":"TypeType","item":{".class":"AnyType","missing_import_name":null,"source_any":null,"type_of_any":2}}],"type_ref":"builtins.tuple"},"pydantic._internal._config.ConfigWrapper",{".class":"UnionType","items":[{".class":"Instance","args":["builtins.str",{".class":"AnyType","missing_import_name":null,"source_any":null,"type_of_any":2}],"type_ref":"builtins.dict"},{".class":"NoneType"}]},{".class":"UnionType","items":[{".class":"Instance","args":[{".class":"AnyType","missing_import_name":null,"source_any":null,"type_of_any":2},{".class":"AnyType","missing_import_name":null,"source_any":null,"type_of_any":2}],"type_ref":"builtins.dict"},{".class":"NoneType"}]}],"bound_args":[],"def_extras":{"first_arg":null},"fallback":"builtins.function","from_concatenate":false,"implicit":false,"is_ellipsis_args":false,"name":"collect_model_fields","ret_type":{".class":"TupleType","implicit":false,"items":[{".class":"Instance","args":["builtins.str","pydantic.fields.FieldInfo"],"type_ref":"builtins.dict"},{".class":"Instance","args":["builtins.str"],"type_ref":"builtins.set"}],"partial_fallback":{".class":"Instance","args":[{".class":"AnyType","missing_import_name":null,"source_any":null,"type_of_any":6}],"type_ref":"builtins.tuple"}},"type_guard":null,"unpack_kwargs":false,"variables":[]}}},"copy":{".class":"SymbolTableNode","cross_ref":"copy.copy","kind":"Gdef","module_hidden":true,"module_public":false},"dataclasses":{".class":"SymbolTableNode","cross_ref":"dataclasses","kind":"Gdef","module_hidden":true,"module_public":false},"get_cls_type_hints_lenient":{".class":"SymbolTableNode","cross_ref":"pydantic._internal._typing_extra.get_cls_type_hints_lenient","kind":"Gdef","module_hidden":true,"module_public":false},"get_type_hints":{".class":"SymbolTableNode","cross_ref":"pydantic._internal._typing_extra.get_type_hints","kind":"Gdef","module_hidden":true,"module_public":false},"get_type_hints_infer_globalns":{".class":"SymbolTableNode","kind":"Gdef","node":{".class":"FuncDef","abstract_status":0,"arg_kinds":[0,1,1],"arg_names":["obj","localns","include_extras"],"dataclass_transform_spec":null,"flags":[],"fullname":"pydantic._internal._fields.get_type_hints_infer_globalns","name":"get_type_hints_infer_globalns","type":{".class":"CallableType","arg_kinds":[0,1,1],"arg_names":["obj","localns","include_extras"],"arg_types":[{".class":"AnyType","missing_import_name":null,"source_any":null,"type_of_any":2},{".class":"UnionType","items":[{".class":"Instance","args":["builtins.str",{".class":"AnyType","missing_import_name":null,"source_any":null,"type_of_any":2}],"type_ref":"builtins.dict"},{".class":"NoneType"}]},"builtins.bool"],"bound_args":[],"def_extras":{"first_arg":null},"fallback":"builtins.function","from_concatenate":false,"implicit":false,"is_ellipsis_args":false,"name":"get_type_hints_infer_globalns","ret_type":{".class":"Instance","args":["builtins.str",{".class":"AnyType","missing_import_name":null,"source_any":null,"type_of_any":2}],"type_ref":"builtins.dict"},"type_guard":null,"unpack_kwargs":false,"variables":[]}}},"is_classvar":{".class":"SymbolTableNode","cross_ref":"pydantic._internal._typing_extra.is_classvar","kind":"Gdef","module_hidden":true,"module_public":false},"is_finalvar":{".class":"SymbolTableNode","cross_ref":"pydantic._internal._typing_extra.is_finalvar","kind":"Gdef","module_hidden":true,"module_public":false},"is_valid_field_name":{".class":"SymbolTableNode","kind":"Gdef","node":{".class":"FuncDef","abstract_status":0,"arg_kinds":[0],"arg_names":["name"],"dataclass_transform_spec":null,"flags":[],"fullname":"pydantic._internal._fields.is_valid_field_name","name":"is_valid_field_name","type":{".class":"CallableType","arg_kinds":[0],"arg_names":["name"],"arg_types":["builtins.str"],"bound_args":[],"def_extras":{"first_arg":null},"fallback":"builtins.function","from_concatenate":false,"implicit":false,"is_ellipsis_args":false,"name":"is_valid_field_name","ret_type":"builtins.bool","type_guard":null,"unpack_kwargs":false,"variables":[]}}},"is_valid_privateattr_name":{".class":"SymbolTableNode","kind":"Gdef","node":{".class":"FuncDef","abstract_status":0,"arg_kinds":[0],"arg_names":["name"],"dataclass_transform_spec":null,"flags":[],"fullname":"pydantic._internal._fields.is_valid_privateattr_name","name":"is_valid_privateattr_name","type":{".class":"CallableType","arg_kinds":[0],"arg_names":["name"],"arg_types":["builtins.str"],"bound_args":[],"def_extras":{"first_arg":null},"fallback":"builtins.function","from_concatenate":false,"implicit":false,"is_ellipsis_args":false,"name":"is_valid_privateattr_name","ret_type":"builtins.bool","type_guard":null,"unpack_kwargs":false,"variables":[]}}},"sys":{".class":"SymbolTableNode","cross_ref":"sys","kind":"Gdef","module_hidden":true,"module_public":false},"warnings":{".class":"SymbolTableNode","cross_ref":"warnings","kind":"Gdef","module_hidden":true,"module_public":false}},"path":"/Users/xli677/.cache/pre-commit/repoehabdpmk/py_env-python3.10/lib/python3.10/site-packages/pydantic/_internal/_fields.py"}